labgrid/__init__.py
labgrid/_version.py
labgrid/binding.py
labgrid/config.py
labgrid/consoleloggingreporter.py
labgrid/environment.py
labgrid/exceptions.py
labgrid/factory.py
labgrid/logging.py
labgrid/step.py
labgrid/stepreporter.py
labgrid/target.py
labgrid/autoinstall/__init__.py
labgrid/autoinstall/main.py
labgrid/driver/__init__.py
labgrid/driver/bareboxdriver.py
labgrid/driver/commandmixin.py
labgrid/driver/common.py
labgrid/driver/consoleexpectmixin.py
labgrid/driver/dediprogflashdriver.py
labgrid/driver/deditecrelaisdriver.py
labgrid/driver/dfudriver.py
labgrid/driver/dockerdriver.py
labgrid/driver/exception.py
labgrid/driver/externalconsoledriver.py
labgrid/driver/fake.py
labgrid/driver/fastbootdriver.py
labgrid/driver/filedigitaloutput.py
labgrid/driver/flashromdriver.py
labgrid/driver/flashscriptdriver.py
labgrid/driver/gpiodriver.py
labgrid/driver/httpdigitaloutput.py
labgrid/driver/httpvideodriver.py
labgrid/driver/lxaiobusdriver.py
labgrid/driver/lxausbmuxdriver.py
labgrid/driver/manualswitchdriver.py
labgrid/driver/modbusdriver.py
labgrid/driver/modbusrtudriver.py
labgrid/driver/mqtt.py
labgrid/driver/networkinterfacedriver.py
labgrid/driver/onewiredriver.py
labgrid/driver/openocddriver.py
labgrid/driver/powerdriver.py
labgrid/driver/provider.py
labgrid/driver/pyvisadriver.py
labgrid/driver/qemudriver.py
labgrid/driver/quartushpsdriver.py
labgrid/driver/rawnetworkinterfacedriver.py
labgrid/driver/resetdriver.py
labgrid/driver/serialdigitaloutput.py
labgrid/driver/serialdriver.py
labgrid/driver/shelldriver.py
labgrid/driver/sigrokdriver.py
labgrid/driver/smallubootdriver.py
labgrid/driver/sshdriver.py
labgrid/driver/ubootdriver.py
labgrid/driver/usbaudiodriver.py
labgrid/driver/usbhidrelay.py
labgrid/driver/usbloader.py
labgrid/driver/usbsdmuxdriver.py
labgrid/driver/usbsdwiredriver.py
labgrid/driver/usbstoragedriver.py
labgrid/driver/usbtmcdriver.py
labgrid/driver/usbvideodriver.py
labgrid/driver/xenadriver.py
labgrid/driver/power/__init__.py
labgrid-25.0.1.dist-info/licenses/COPYING
labgrid-25.0.1.dist-info/licenses/LICENSE
labgrid-25.0.1.dist-info/METADATA
labgrid-25.0.1.dist-info/WHEEL
labgrid-25.0.1.dist-info/entry_points.txt
labgrid-25.0.1.dist-info/top_level.txt
labgrid-25.0.1.dist-info/RECORD
