Metadata-Version: 2.4
Name: labgrid
Version: 25.0.1
Summary: embedded systems control library for development, testing and installation
Author-email: Rouven Czerwinski <entwicklung@pengutronix.de>, Jan Luebbe <entwicklung@pengutronix.de>
License: Copyright (C) 2016-2017 Pengutronix, Jan Luebbe <entwicklung@pengutronix.de>
Project-URL: Homepage, https://github.com/labgrid-project/labgrid
Project-URL: Bug Tracker, https://github.com/labgrid-project/labgrid/issues
Classifier: Intended Audience :: Developers
Classifier: Development Status :: 5 - Production/Stable
Classifier: Operating System :: POSIX :: Linux
Classifier: Topic :: Software Development :: Testing
Classifier: Framework :: Pytest
Classifier: Programming Language :: Python :: 3 :: Only
Classifier: Programming Language :: Python :: 3.9
Classifier: Programming Language :: Python :: 3.10
Classifier: Programming Language :: Python :: 3.11
Classifier: Programming Language :: Python :: 3.12
Classifier: Programming Language :: Python :: 3.13
Classifier: License :: OSI Approved :: GNU Lesser General Public License v2 or later (LGPLv2+)
Requires-Python: >=3.9
License-File: LICENSE
License-File: COPYING
Requires-Dist: ansicolors>=1.1.8
Requires-Dist: attrs>=21.4.0
Requires-Dist: grpcio<2.0.0,>=1.64.1
Requires-Dist: grpcio-reflection<2.0.0,>=1.64.1
Requires-Dist: protobuf>=5.27.0
Requires-Dist: jinja2>=3.0.2
Requires-Dist: pexpect>=4.8.0
Requires-Dist: pyserial-labgrid>=3.4.0.1
Requires-Dist: pytest>=7.0.0
Requires-Dist: pyudev>=0.22.0
Requires-Dist: pyusb>=1.2.1
Requires-Dist: PyYAML>=6.0.1
Requires-Dist: requests>=2.26.0
Requires-Dist: xmodem>=0.4.6
Provides-Extra: doc
Requires-Dist: sphinx_rtd_theme>=1.0.0; extra == "doc"
Requires-Dist: Sphinx>=2.0.0; extra == "doc"
Provides-Extra: docker
Requires-Dist: docker>=5.0.2; extra == "docker"
Provides-Extra: graph
Requires-Dist: graphviz>=0.17.0; extra == "graph"
Provides-Extra: kasa
Requires-Dist: python-kasa>=0.7.0; extra == "kasa"
Provides-Extra: modbus
Requires-Dist: pyModbusTCP>=0.2.0; extra == "modbus"
Provides-Extra: modbusrtu
Requires-Dist: minimalmodbus>=1.0.2; extra == "modbusrtu"
Provides-Extra: mqtt
Requires-Dist: paho-mqtt>=2.0.0; extra == "mqtt"
Provides-Extra: onewire
Requires-Dist: onewire>=0.2; extra == "onewire"
Provides-Extra: pyvisa
Requires-Dist: pyvisa>=1.11.3; extra == "pyvisa"
Requires-Dist: PyVISA-py>=0.5.2; extra == "pyvisa"
Provides-Extra: snmp
Requires-Dist: pysnmp<6,>=4.4.12; extra == "snmp"
Requires-Dist: pyasn1<0.6.1; extra == "snmp"
Provides-Extra: vxi11
Requires-Dist: python-vxi11>=0.9; extra == "vxi11"
Provides-Extra: xena
Requires-Dist: xenavalkyrie>=3.0.1; extra == "xena"
Provides-Extra: deb
Requires-Dist: labgrid[modbus,onewire,snmp]; extra == "deb"
Provides-Extra: dev
Requires-Dist: labgrid[doc,docker,graph,kasa,modbus,modbusrtu,mqtt,onewire,pyvisa,snmp,vxi11]; extra == "dev"
Requires-Dist: psutil>=5.8.0; extra == "dev"
Requires-Dist: pytest-benchmark>=4.0.0; extra == "dev"
Requires-Dist: pytest-cov>=3.0.0; extra == "dev"
Requires-Dist: pytest-dependency>=0.5.1; extra == "dev"
Requires-Dist: pytest-isort>=2.0.0; extra == "dev"
Requires-Dist: pytest-mock>=3.6.1; extra == "dev"
Requires-Dist: pylint>=3.0.0; extra == "dev"
Requires-Dist: ruff>=0.5.7; extra == "dev"
Requires-Dist: pystuck; extra == "dev"
Requires-Dist: grpcio-channelz<2.0.0,>=1.64.1; extra == "dev"
Dynamic: license-file
